boundry/__init__.py
boundry-0.0.1.dist-info/METADATA
boundry-0.0.1.dist-info/WHEEL
boundry-0.0.1.dist-info/licenses/LICENSE
boundry-0.0.1.dist-info/RECORD
