Metadata-Version: 2.4
Name: boundry
Version: 0.0.1
Summary: A Python package (under development)
Project-URL: Homepage, https://github.com/bryanbriney/boundry
Project-URL: Repository, https://github.com/bryanbriney/boundry
Author: Bryan Briney
License-Expression: MIT
License-File: LICENSE
Classifier: Development Status :: 1 - Planning
Classifier: License :: OSI Approved :: MIT License
Classifier: Programming Language :: Python :: 3
Classifier: Programming Language :: Python :: 3.8
Classifier: Programming Language :: Python :: 3.9
Classifier: Programming Language :: Python :: 3.10
Classifier: Programming Language :: Python :: 3.11
Classifier: Programming Language :: Python :: 3.12
Requires-Python: >=3.8
